novnc/__init__.py
novnc/__main__.py
novnc/resources/novnc_server.zip
novnc-1.3.0.dist-info/METADATA
novnc-1.3.0.dist-info/WHEEL
novnc-1.3.0.dist-info/entry_points.txt
novnc-1.3.0.dist-info/top_level.txt
novnc-1.3.0.dist-info/RECORD
