Metadata-Version: 2.4
Name: novnc
Version: 1.3.0
Summary: noVNC is a Python-based server that integrates noVNC and websockify to provide a web-based VNC client, enabling remote desktop access via a web browser.
Author: Ankush Bhagat
Author-email: <ankushbhagatofficial@gmail.com>
Keywords: python,novnc,vnc,web
Classifier: Intended Audience :: Developers
Classifier: Programming Language :: Python :: 3
Classifier: Operating System :: Unix
Classifier: Operating System :: MacOS :: MacOS X
Classifier: Operating System :: Microsoft :: Windows
Requires-Dist: websockify
Dynamic: author
Dynamic: author-email
Dynamic: classifier
Dynamic: description
Dynamic: description-content-type
Dynamic: keywords
Dynamic: requires-dist
Dynamic: summary
